Workbook

Sheet CorST
A1: Word | B1: Частота-CorST | C1: IPM-CorST | D1: Ранг-CorST | E1: сколько раз встречается в столбце | F1: номер строки в rlc | G1: IPM_rlc
A2: в | B2: 35889 | C2: 11520.564 | D2: 1 | E2: =COUNTIF(B:B,B2) -> 1 | F2: =MATCH(A2,RLC!A:A,0) -> 3 | G2: {=INDEX(RLC!C:C,CorST!F2)} -> 37993.234
A3: и | B3: 31435 | C3: 10090.806 | D3: =D2+IF(B3<>B2,E2,0) -> 2 | E3: =COUNTIF(B:B,B3) -> 1 | F3: =MATCH(A3,RLC!A:A,0) -> 2 | G3: {=INDEX(RLC!C:C,CorST!F3)} -> 38334.702
A4: на | B4: 13212 | C4: 4241.1239 | D4: =D3+IF(B4<>B3,E3,0) -> 3 | E4: =COUNTIF(B:B,B4) -> 1 | F4: =MATCH(A4,RLC!A:A,0) -> 5 | G4: {=INDEX(RLC!C:C,CorST!F4)} -> 13265.412
A5: не | B5: 11811 | C5: 3791.3953 | D5: =D4+IF(B5<>B4,E4,0) -> 4 | E5: =COUNTIF(B:B,B5) -> 1 | F5: =MATCH(A5,RLC!A:A,0) -> 6 | G5: {=INDEX(RLC!C:C,CorST!F5)} -> 12860.168
A6: с | B6: 11363 | C6: 3647.5848 | D6: =D5+IF(B6<>B5,E5,0) -> 5 | E6: =COUNTIF(B:B,B6) -> 1 | F6: =MATCH(A6,RLC!A:A,0) -> 8 | G6: {=INDEX(RLC!C:C,CorST!F6)} -> 9178.432
A7: что | B7: 10265 | C7: 3295.1208 | D7: =D6+IF(B7<>B6,E6,0) -> 6 | E7: =COUNTIF(B:B,B7) -> 1 | F7: =MATCH(A7,RLC!A:A,0) -> 4 | G7: {=INDEX(RLC!C:C,CorST!F7)} -> 16305.402
A8: как | B8: 7396 | C8: 2374.1562 | D8: =D7+IF(B8<>B7,E7,0) -> 7 | E8: =COUNTIF(B:B,B8) -> 1 | F8: =MATCH(A8,RLC!A:A,0) -> 9 | G8: {=INDEX(RLC!C:C,CorST!F8)} -> 8273.6097
A9: к | B9: 6790 | C9: 2179.6269 | D9: =D8+IF(B9<>B8,E8,0) -> 8 | E9: =COUNTIF(B:B,B9) -> 1 | F9: =MATCH(A9,RLC!A:A,0) -> 15 | G9: {=INDEX(RLC!C:C,CorST!F9)} -> 4742.0127
A10: а | B10: 5924 | C10: 1901.6362 | D10: =D9+IF(B10<>B9,E9,0) -> 9 | E10: =COUNTIF(B:B,B10) -> 1 | F10: =MATCH(A10,RLC!A:A,0) -> 20 | G10: {=INDEX(RLC!C:C,CorST!F10)} -> 3449.2197
A11: для | B11: 5652 | C11: 1814.3227 | D11: =D10+IF(B11<>B10,E10,0) -> 10 | E11: =COUNTIF(B:B,B11) -> 1 | F11: =MATCH(A11,RLC!A:A,0) -> 14 | G11: {=INDEX(RLC!C:C,CorST!F11)} -> 5009.0748
A12: по | B12: 5634 | C12: 1808.5447 | D12: =D11+IF(B12<>B11,E11,0) -> 11 | E12: =COUNTIF(B:B,B12) -> 1 | F12: =MATCH(A12,RLC!A:A,0) -> 16 | G12: {=INDEX(RLC!C:C,CorST!F12)} -> 4641.034
A13: о | B13: 4912 | C13: 1576.7787 | D13: =D12+IF(B13<>B12,E12,0) -> 12 | E13: =COUNTIF(B:B,B13) -> 1 | F13: =MATCH(A13,RLC!A:A,0) -> 13 | G13: {=INDEX(RLC!C:C,CorST!F13)} -> 5022.3615
A14: из | B14: 4365 | C14: 1401.1887 | D14: =D13+IF(B14<>B13,E13,0) -> 13 | E14: =COUNTIF(B:B,B14) -> 1 | F14: =MATCH(A14,RLC!A:A,0) -> 17 | G14: {=INDEX(RLC!C:C,CorST!F14)} -> 4432.4333
... A1349: форм | B1349: 92 | C1349: 29.532501 | D1349: =D1348+IF(B1349<>B1348,E1348,0) -> 1326 | E1349: =COUNTIF(B:B,B1349) -> 26 | F1349: =MATCH(A1349,RLC!A:A,0) -> 5289 | G1349: {=INDEX(RLC!C:C,CorST!F1349)} -> 21.258673
A1350: школе | B1350: 92 | C1350: 29.532501 | D1350: =D1349+IF(B1350<>B1349,E1349,0) -> 1326 | E1350: =COUNTIF(B:B,B1350) -> 26 | F1350: =MATCH(A1350,RLC!A:A,0) -> 404 | G1350: {=INDEX(RLC!C:C,CorST!F1350)} -> 259.09008 | H1350: =C1350>F1350 -> FALSE
A1351: элементов | B1351: 92 | C1351: 29.532501 | D1351: =D1350+IF(B1351<>B1350,E1350,0) -> 1326 | E1351: =COUNTIF(B:B,B1351) -> 26 | F1351: =MATCH(A1351,RLC!A:A,0) -> 4112 | G1351: {=INDEX(RLC!C:C,CorST!F1351)} -> 27.902008
A1352: этими | B1352: 92 | C1352: 29.532501 | D1352: =D1351+IF(B1352<>B1351,E1351,0) -> 1326 | E1352: =COUNTIF(B:B,B1352) -> 26 | F1352: =MATCH(A1352,RLC!A:A,0) -> 1492 | G1352: {=INDEX(RLC!C:C,CorST!F1352)} -> 77.062689
A1353: артикля | B1353: 91 | C1353: 29.211495 | D1353: =D1352+IF(B1353<>B1352,E1352,0) -> 1352 | E1353: =COUNTIF(B:B,B1353) -> 12 | F1353: =MATCH(A1353,RLC!A:A,0) -> #N/A | G1353: {=INDEX(RLC!C:C,CorST!F1353)} -> #N/A
A1354: всему | B1354: 91 | C1354: 29.211495 | D1354: =D1353+IF(B1354<>B1353,E1353,0) -> 1352 | E1354: =COUNTIF(B:B,B1354) -> 12 | F1354: =MATCH(A1354,RLC!A:A,0) -> 741 | G1354: {=INDEX(RLC!C:C,CorST!F1354)} -> 144.82471
A1355: выполнения | B1355: 91 | C1355: 29.211495 | D1355: =D1354+IF(B1355<>B1354,E1354,0) -> 1352 | E1355: =COUNTIF(B:B,B1355) -> 12 | F1355: =MATCH(A1355,RLC!A:A,0) -> #N/A | G1355: {=INDEX(RLC!C:C,CorST!F1355)} -> #N/A
A1356: достоевский | B1356: 91 | C1356: 29.211495 | D1356: =D1355+IF(B1356<>B1355,E1355,0) -> 1352 | E1356: =COUNTIF(B:B,B1356) -> 12 | F1356: =MATCH(A1356,RLC!A:A,0) -> #N/A | G1356: {=INDEX(RLC!C:C,CorST!F1356)} -> #N/A
A1357: менеджмента | B1357: 91 | C1357: 29.211495 | D1357: =D1356+IF(B1357<>B1356,E1356,0) -> 1352 | E1357: =COUNTIF(B:B,B1357) -> 12 | F1357: =MATCH(A1357,RLC!A:A,0) -> 2858 | G1357: {=INDEX(RLC!C:C,CorST!F1357)} -> 39.860012
A1358: наша | B1358: 91 | C1358: 29.211495 | D1358: =D1357+IF(B1358<>B1357,E1357,0) -> 1352 | E1358: =COUNTIF(B:B,B1358) -> 12 | F1358: =MATCH(A1358,RLC!A:A,0) -> 551 | G1358: {=INDEX(RLC!C:C,CorST!F1358)} -> 193.98539
A1359: поднятая | B1359: 91 | C1359: 29.211495 | D1359: =D1358+IF(B1359<>B1358,E1358,0) -> 1352 | E1359: =COUNTIF(B:B,B1359) -> 12 | F1359: =MATCH(A1359,RLC!A:A,0) -> #N/A | G1359: {=INDEX(RLC!C:C,CorST!F1359)} -> #N/A
A1360: постепенно | B1360: 91 | C1360: 29.211495 | D1360: =D1359+IF(B1360<>B1359,E1359,0) -> 1352 | E1360: =COUNTIF(B:B,B1360) -> 12 | F1360: =MATCH(A1360,RLC!A:A,0) -> 2469 | G1360: {=INDEX(RLC!C:C,CorST!F1360)} -> 46.503347
A1361: рублей | B1361: 91 | C1361: 29.211495 | D1361: =D1360+IF(B1361<>B1360,E1360,0) -> 1352 | E1361: =COUNTIF(B:B,B1361) -> 12 | F1361: =MATCH(A1361,RLC!A:A,0) -> 1697 | G1361: {=INDEX(RLC!C:C,CorST!F1361)} -> 67.76202
A1362: сегодняшний | B1362: 91 | C1362: 29.211495 | D1362: =D1361+IF(B1362<>B1361,E1361,0) -> 1352 | E1362: =COUNTIF(B:B,B1362) -> 12 | F1362: =MATCH(A1362,RLC!A:A,0) -> 1873 | G1362: {=INDEX(RLC!C:C,CorST!F1362)} -> 62.447352
... A1716: чехов | B1716: 73 | C1716: 23.433397 | D1716: =D1715+IF(B1716<>B1715,E1715,0) -> 1684 | E1716: =COUNTIF(B:B,B1716) -> 35 | F1716: =MATCH(A1716,RLC!A:A,0) -> #N/A | G1716: {=INDEX(RLC!C:C,CorST!F1716)} -> #N/A
A1717: шапочка | B1717: 73 | C1717: 23.433397 | D1717: =D1716+IF(B1717<>B1716,E1716,0) -> 1684 | E1717: =COUNTIF(B:B,B1717) -> 35 | F1717: =MATCH(A1717,RLC!A:A,0) -> 3340 | G1717: {=INDEX(RLC!C:C,CorST!F1717)} -> 34.545343 | H1717: =C1717>F1717 -> FALSE
A1718: широко | B1718: 73 | C1718: 23.433397 | D1718: =D1717+IF(B1718<>B1717,E1717,0) -> 1684 | E1718: =COUNTIF(B:B,B1718) -> 35 | F1718: =MATCH(A1718,RLC!A:A,0) -> 1585 | G1718: {=INDEX(RLC!C:C,CorST!F1718)} -> 73.076688 | H1718: =C1718>F1718 -> FALSE
A1719: эмоций | B1719: 73 | C1719: 23.433397 | D1719: =D1718+IF(B1719<>B1718,E1718,0) -> 1684 | E1719: =COUNTIF(B:B,B1719) -> 35 | F1719: =MATCH(A1719,RLC!A:A,0) -> 6913 | G1719: {=INDEX(RLC!C:C,CorST!F1719)} -> 15.944005
A1720: большие | B1720: 72 | C1720: 23.112392 | D1720: =D1719+IF(B1720<>B1719,E1719,0) -> 1719 | E1720: =COUNTIF(B:B,B1720) -> 42 | F1720: =MATCH(A1720,RLC!A:A,0) -> 837 | G1720: {=INDEX(RLC!C:C,CorST!F1720)} -> 128.8807
A1721: большого | B1721: 72 | C1721: 23.112392 | D1721: =D1720+IF(B1721<>B1720,E1720,0) -> 1719 | E1721: =COUNTIF(B:B,B1721) -> 42 | F1721: =MATCH(A1721,RLC!A:A,0) -> 2651 | G1721: {=INDEX(RLC!C:C,CorST!F1721)} -> 42.517346
A1722: ведет | B1722: 72 | C1722: 23.112392 | D1722: =D1721+IF(B1722<>B1721,E1721,0) -> 1719 | E1722: =COUNTIF(B:B,B1722) -> 42 | F1722: =MATCH(A1722,RLC!A:A,0) -> 3483 | G1722: {=INDEX(RLC!C:C,CorST!F1722)} -> 31.888009
A1723: вниз | B1723: 72 | C1723: 23.112392 | D1723: =D1722+IF(B1723<>B1722,E1722,0) -> 1719 | E1723: =COUNTIF(B:B,B1723) -> 42 | F1723: =MATCH(A1723,RLC!A:A,0) -> 2832 | G1723: {=INDEX(RLC!C:C,CorST!F1723)} -> 39.860012
A1724: вузов | B1724: 72 | C1724: 23.112392 | D1724: =D1723+IF(B1724<>B1723,E1723,0) -> 1719 | E1724: =COUNTIF(B:B,B1724) -> 42 | F1724: =MATCH(A1724,RLC!A:A,0) -> 6052 | G1724: {=INDEX(RLC!C:C,CorST!F1724)} -> 17.272672
A1725: выражений | B1725: 72 | C1725: 23.112392 | D1725: =D1724+IF(B1725<>B1724,E1724,0) -> 1719 | E1725: =COUNTIF(B:B,B1725) -> 42 | F1725: =MATCH(A1725,RLC!A:A,0) -> 3786 | G1725: {=INDEX(RLC!C:C,CorST!F1725)} -> 29.230675
A1726: гражданским | B1726: 72 | C1726: 23.112392 | D1726: =D1725+IF(B1726<>B1725,E1725,0) -> 1719 | E1726: =COUNTIF(B:B,B1726) -> 42 | F1726: =MATCH(A1726,RLC!A:A,0) -> #N/A | G1726: {=INDEX(RLC!C:C,CorST!F1726)} -> #N/A
A1727: изучить | B1727: 72 | C1727: 23.112392 | D1727: =D1726+IF(B1727<>B1726,E1726,0) -> 1719 | E1727: =COUNTIF(B:B,B1727) -> 42 | F1727: =MATCH(A1727,RLC!A:A,0) -> 4372 | G1727: {=INDEX(RLC!C:C,CorST!F1727)} -> 25.244674
A1728: ин | B1728: 72 | C1728: 23.112392 | D1728: =D1727+IF(B1728<>B1727,E1727,0) -> 1719 | E1728: =COUNTIF(B:B,B1728) -> 42 | F1728: =MATCH(A1728,RLC!A:A,0) -> #N/A | G1728: {=INDEX(RLC!C:C,CorST!F1728)} -> #N/A
A1729: интернета | B1729: 72 | C1729: 23.112392 | D1729: =D1728+IF(B1729<>B1728,E1728,0) -> 1719 | E1729: =COUNTIF(B:B,B1729) -> 42 | F1729: =MATCH(A1729,RLC!A:A,0) -> 2960 | G1729: {=INDEX(RLC!C:C,CorST!F1729)} -> 38.531345
A1730: когнитивных | B1730: 72 | C1730: 23.112392 | D1730: =D1729+IF(B1730<>B1729,E1729,0) -> 1719 | E1730: =COUNTIF(B:B,B1730) -> 42 | F1730: =MATCH(A1730,RLC!A:A,0) -> #N/A | G1730: {=INDEX(RLC!C:C,CorST!F1730)} -> #N/A
... A2090: чтение | B2090: 61 | C2090: 19.581332 | D2090: =D2089+IF(B2090<>B2089,E2089,0) -> 2063 | E2090: =COUNTIF(B:B,B2090) -> 28 | F2090: =MATCH(A2090,RLC!A:A,0) -> 2647 | G2090: {=INDEX(RLC!C:C,CorST!F2090)} -> 43.846013
A2091: школы | B2091: 61 | C2091: 19.581332 | D2091: =D2090+IF(B2091<>B2090,E2090,0) -> 2063 | E2091: =COUNTIF(B:B,B2091) -> 28 | F2091: =MATCH(A2091,RLC!A:A,0) -> 542 | G2091: {=INDEX(RLC!C:C,CorST!F2091)} -> 197.97139 | H2091: =C2091>F2091 -> FALSE
A2092: больших | B2092: 60 | C2092: 19.260326 | D2092: =D2091+IF(B2092<>B2091,E2091,0) -> 2091 | E2092: =COUNTIF(B:B,B2092) -> 37 | F2092: =MATCH(A2092,RLC!A:A,0) -> 1082 | G2092: {=INDEX(RLC!C:C,CorST!F2092)} -> 102.30736
A2093: будем | B2093: 60 | C2093: 19.260326 | D2093: =D2092+IF(B2093<>B2092,E2092,0) -> 2091 | E2093: =COUNTIF(B:B,B2093) -> 37 | F2093: =MATCH(A2093,RLC!A:A,0) -> 1097 | G2093: {=INDEX(RLC!C:C,CorST!F2093)} -> 100.9787
A2094: вариативность | B2094: 60 | C2094: 19.260326 | D2094: =D2093+IF(B2094<>B2093,E2093,0) -> 2091 | E2094: =COUNTIF(B:B,B2094) -> 37 | F2094: =MATCH(A2094,RLC!A:A,0) -> #N/A | G2094: {=INDEX(RLC!C:C,CorST!F2094)} -> #N/A
A2095: возмещения | B2095: 60 | C2095: 19.260326 | D2095: =D2094+IF(B2095<>B2094,E2094,0) -> 2091 | E2095: =COUNTIF(B:B,B2095) -> 37 | F2095: =MATCH(A2095,RLC!A:A,0) -> #N/A | G2095: {=INDEX(RLC!C:C,CorST!F2095)} -> #N/A
A2096: возможностей | B2096: 60 | C2096: 19.260326 | D2096: =D2095+IF(B2096<>B2095,E2095,0) -> 2091 | E2096: =COUNTIF(B:B,B2096) -> 37 | F2096: =MATCH(A2096,RLC!A:A,0) -> 2835 | G2096: {=INDEX(RLC!C:C,CorST!F2096)} -> 39.860012
A2097: выяснить | B2097: 60 | C2097: 19.260326 | D2097: =D2096+IF(B2097<>B2096,E2096,0) -> 2091 | E2097: =COUNTIF(B:B,B2097) -> 37 | F2097: =MATCH(A2097,RLC!A:A,0) -> 7547 | G2097: {=INDEX(RLC!C:C,CorST!F2097)} -> 13.286671
A2098: гипотез | B2098: 60 | C2098: 19.260326 | D2098: =D2097+IF(B2098<>B2097,E2097,0) -> 2091 | E2098: =COUNTIF(B:B,B2098) -> 37 | F2098: =MATCH(A2098,RLC!A:A,0) -> #N/A | G2098: {=INDEX(RLC!C:C,CorST!F2098)} -> #N/A
A2099: голове | B2099: 60 | C2099: 19.260326 | D2099: =D2098+IF(B2099<>B2098,E2098,0) -> 2091 | E2099: =COUNTIF(B:B,B2099) -> 37 | F2099: =MATCH(A2099,RLC!A:A,0) -> 2131 | G2099: {=INDEX(RLC!C:C,CorST!F2099)} -> 53.146682
A2100: гражданском | B2100: 60 | C2100: 19.260326 | D2100: =D2099+IF(B2100<>B2099,E2099,0) -> 2091 | E2100: =COUNTIF(B:B,B2100) -> 37 | F2100: =MATCH(A2100,RLC!A:A,0) -> #N/A | G2100: {=INDEX(RLC!C:C,CorST!F2100)} -> #N/A
A2101: дается | B2101: 60 | C2101: 19.260326 | D2101: =D2100+IF(B2101<>B2100,E2100,0) -> 2091 | E2101: =COUNTIF(B:B,B2101) -> 37 | F2101: =MATCH(A2101,RLC!A:A,0) -> 4145 | G2101: {=INDEX(RLC!C:C,CorST!F2101)} -> 26.573341
A2102: дальнейшего | B2102: 60 | C2102: 19.260326 | D2102: =D2101+IF(B2102<>B2101,E2101,0) -> 2091 | E2102: =COUNTIF(B:B,B2102) -> 37 | F2102: =MATCH(A2102,RLC!A:A,0) -> #N/A | G2102: {=INDEX(RLC!C:C,CorST!F2102)} -> #N/A
A2103: другая | B2103: 60 | C2103: 19.260326 | D2103: =D2102+IF(B2103<>B2102,E2102,0) -> 2091 | E2103: =COUNTIF(B:B,B2103) -> 37 | F2103: =MATCH(A2103,RLC!A:A,0) -> 1157 | G2103: {=INDEX(RLC!C:C,CorST!F2103)} -> 96.992695
... A2510: фоне | B2510: 50 | C2510: 16.050272 | D2510: =D2509+IF(B2510<>B2509,E2509,0) -> 2456 | E2510: =COUNTIF(B:B,B2510) -> 55 | F2510: =MATCH(A2510,RLC!A:A,0) -> #N/A | G2510: {=INDEX(RLC!C:C,CorST!F2510)} -> #N/A
A2511: широкий | B2511: 50 | C2511: 16.050272 | D2511: =D2510+IF(B2511<>B2510,E2510,0) -> 2456 | E2511: =COUNTIF(B:B,B2511) -> 55 | F2511: =MATCH(A2511,RLC!A:A,0) -> 6907 | G2511: {=INDEX(RLC!C:C,CorST!F2511)} -> 15.944005 | H2511: =C2511>F2511 -> FALSE
A2512: адресован | B2512: 49 | C2512: 15.729267 | D2512: =D2511+IF(B2512<>B2511,E2511,0) -> 2511 | E2512: =COUNTIF(B:B,B2512) -> 45 | F2512: =MATCH(A2512,RLC!A:A,0) -> #N/A | G2512: {=INDEX(RLC!C:C,CorST!F2512)} -> #N/A
A2513: база | B2513: 49 | C2513: 15.729267 | D2513: =D2512+IF(B2513<>B2512,E2512,0) -> 2511 | E2513: =COUNTIF(B:B,B2513) -> 45 | F2513: =MATCH(A2513,RLC!A:A,0) -> #N/A | G2513: {=INDEX(RLC!C:C,CorST!F2513)} -> #N/A
A2514: вариативности | B2514: 49 | C2514: 15.729267 | D2514: =D2513+IF(B2514<>B2513,E2513,0) -> 2511 | E2514: =COUNTIF(B:B,B2514) -> 45 | F2514: =MATCH(A2514,RLC!A:A,0) -> #N/A | G2514: {=INDEX(RLC!C:C,CorST!F2514)} -> #N/A
A2515: введения | B2515: 49 | C2515: 15.729267 | D2515: =D2514+IF(B2515<>B2514,E2514,0) -> 2511 | E2515: =COUNTIF(B:B,B2515) -> 45 | F2515: =MATCH(A2515,RLC!A:A,0) -> 7509 | G2515: {=INDEX(RLC!C:C,CorST!F2515)} -> 13.286671
A2516: видел | B2516: 49 | C2516: 15.729267 | D2516: =D2515+IF(B2516<>B2515,E2515,0) -> 2511 | E2516: =COUNTIF(B:B,B2516) -> 45 | F2516: =MATCH(A2516,RLC!A:A,0) -> 1926 | G2516: {=INDEX(RLC!C:C,CorST!F2516)} -> 59.790017
A2517: высокий | B2517: 49 | C2517: 15.729267 | D2517: =D2516+IF(B2517<>B2516,E2516,0) -> 2511 | E2517: =COUNTIF(B:B,B2517) -> 45 | F2517: =MATCH(A2517,RLC!A:A,0) -> 2129 | G2517: {=INDEX(RLC!C:C,CorST!F2517)} -> 53.146682
A2518: выходит | B2518: 49 | C2518: 15.729267 | D2518: =D2517+IF(B2518<>B2517,E2517,0) -> 2511 | E2518: =COUNTIF(B:B,B2518) -> 45 | F2518: =MATCH(A2518,RLC!A:A,0) -> 3637 | G2518: {=INDEX(RLC!C:C,CorST!F2518)} -> 30.559342
A2519: герои | B2519: 49 | C2519: 15.729267 | D2519: =D2518+IF(B2519<>B2518,E2518,0) -> 2511 | E2519: =COUNTIF(B:B,B2519) -> 45 | F2519: =MATCH(A2519,RLC!A:A,0) -> 2502 | G2519: {=INDEX(RLC!C:C,CorST!F2519)} -> 45.17468
A2520: глагольных | B2520: 49 | C2520: 15.729267 | D2520: =D2519+IF(B2520<>B2519,E2519,0) -> 2511 | E2520: =COUNTIF(B:B,B2520) -> 45 | F2520: =MATCH(A2520,RLC!A:A,0) -> #N/A | G2520: {=INDEX(RLC!C:C,CorST!F2520)} -> #N/A
A2521: гпк | B2521: 49 | C2521: 15.729267 | D2521: =D2520+IF(B2521<>B2520,E2520,0) -> 2511 | E2521: =COUNTIF(B:B,B2521) -> 45 | F2521: =MATCH(A2521,RLC!A:A,0) -> #N/A | G2521: {=INDEX(RLC!C:C,CorST!F2521)} -> #N/A
A2522: егэ | B2522: 49 | C2522: 15.729267 | D2522: =D2521+IF(B2522<>B2521,E2521,0) -> 2511 | E2522: =COUNTIF(B:B,B2522) -> 45 | F2522: =MATCH(A2522,RLC!A:A,0) -> 3049 | G2522: {=INDEX(RLC!C:C,CorST!F2522)} -> 37.202678
A2523: единственный | B2523: 49 | C2523: 15.729267 | D2523: =D2522+IF(B2523<>B2522,E2522,0) -> 2511 | E2523: =COUNTIF(B:B,B2523) -> 45 | F2523: =MATCH(A2523,RLC!A:A,0) -> 1892 | G2523: {=INDEX(RLC!C:C,CorST!F2523)} -> 61.118685
... A2664: человеке | B2664: 47 | C2664: 15.087256 | D2664: =D2663+IF(B2664<>B2663,E2663,0) -> 2608 | E2664: =COUNTIF(B:B,B2664) -> 57 | F2664: =MATCH(A2664,RLC!A:A,0) -> 2556 | G2664: {=INDEX(RLC!C:C,CorST!F2664)} -> 45.17468
A2665: шаг | B2665: 47 | C2665: 15.087256 | D2665: =D2664+IF(B2665<>B2664,E2664,0) -> 2608 | E2665: =COUNTIF(B:B,B2665) -> 57 | F2665: =MATCH(A2665,RLC!A:A,0) -> 2738 | G2665: {=INDEX(RLC!C:C,CorST!F2665)} -> 42.517346 | H2665: =C2665>F2665 -> FALSE
A2666: авторских | B2666: 46 | C2666: 14.76625 | D2666: =D2665+IF(B2666<>B2665,E2665,0) -> 2665 | E2666: =COUNTIF(B:B,B2666) -> 72 | F2666: =MATCH(A2666,RLC!A:A,0) -> #N/A | G2666: {=INDEX(RLC!C:C,CorST!F2666)} -> #N/A
A2667: будь | B2667: 46 | C2667: 14.76625 | D2667: =D2666+IF(B2667<>B2666,E2666,0) -> 2665 | E2667: =COUNTIF(B:B,B2667) -> 72 | F2667: =MATCH(A2667,RLC!A:A,0) -> 3245 | G2667: {=INDEX(RLC!C:C,CorST!F2667)} -> 34.545343
A2668: бытия | B2668: 46 | C2668: 14.76625 | D2668: =D2667+IF(B2668<>B2667,E2667,0) -> 2665 | E2668: =COUNTIF(B:B,B2668) -> 72 | F2668: =MATCH(A2668,RLC!A:A,0) -> #N/A | G2668: {=INDEX(RLC!C:C,CorST!F2668)} -> #N/A
A2669: вводит | B2669: 46 | C2669: 14.76625 | D2669: =D2668+IF(B2669<>B2668,E2668,0) -> 2665 | E2669: =COUNTIF(B:B,B2669) -> 72 | F2669: =MATCH(A2669,RLC!A:A,0) -> #N/A | G2669: {=INDEX(RLC!C:C,CorST!F2669)} -> #N/A
A2670: вещь | B2670: 46 | C2670: 14.76625 | D2670: =D2669+IF(B2670<>B2669,E2669,0) -> 2665 | E2670: =COUNTIF(B:B,B2670) -> 72 | F2670: =MATCH(A2670,RLC!A:A,0) -> 2655 | G2670: {=INDEX(RLC!C:C,CorST!F2670)} -> 42.517346
A2671: взаимодействии | B2671: 46 | C2671: 14.76625 | D2671: =D2670+IF(B2671<>B2670,E2670,0) -> 2665 | E2671: =COUNTIF(B:B,B2671) -> 72 | F2671: =MATCH(A2671,RLC!A:A,0) -> #N/A | G2671: {=INDEX(RLC!C:C,CorST!F2671)} -> #N/A
A2672: выборки | B2672: 46 | C2672: 14.76625 | D2672: =D2671+IF(B2672<>B2671,E2671,0) -> 2665 | E2672: =COUNTIF(B:B,B2672) -> 72 | F2672: =MATCH(A2672,RLC!A:A,0) -> #N/A | G2672: {=INDEX(RLC!C:C,CorST!F2672)} -> #N/A
A2673: выделены | B2673: 46 | C2673: 14.76625 | D2673: =D2672+IF(B2673<>B2672,E2672,0) -> 2665 | E2673: =COUNTIF(B:B,B2673) -> 72 | F2673: =MATCH(A2673,RLC!A:A,0) -> #N/A | G2673: {=INDEX(RLC!C:C,CorST!F2673)} -> #N/A
A2674: гипотезу | B2674: 46 | C2674: 14.76625 | D2674: =D2673+IF(B2674<>B2673,E2673,0) -> 2665 | E2674: =COUNTIF(B:B,B2674) -> 72 | F2674: =MATCH(A2674,RLC!A:A,0) -> #N/A | G2674: {=INDEX(RLC!C:C,CorST!F2674)} -> #N/A
A2675: государств | B2675: 46 | C2675: 14.76625 | D2675: =D2674+IF(B2675<>B2674,E2674,0) -> 2665 | E2675: =COUNTIF(B:B,B2675) -> 72 | F2675: =MATCH(A2675,RLC!A:A,0) -> 991 | G2675: {=INDEX(RLC!C:C,CorST!F2675)} -> 111.60803
A2676: доме | B2676: 46 | C2676: 14.76625 | D2676: =D2675+IF(B2676<>B2675,E2675,0) -> 2665 | E2676: =COUNTIF(B:B,B2676) -> 72 | F2676: =MATCH(A2676,RLC!A:A,0) -> 907 | G2676: {=INDEX(RLC!C:C,CorST!F2676)} -> 120.9087
A2677: думать | B2677: 46 | C2677: 14.76625 | D2677: =D2676+IF(B2677<>B2676,E2676,0) -> 2665 | E2677: =COUNTIF(B:B,B2677) -> 72 | F2677: =MATCH(A2677,RLC!A:A,0) -> 720 | G2677: {=INDEX(RLC!C:C,CorST!F2677)} -> 147.48204
... A2830: ценностей | B2830: 44 | C2830: 14.124239 | D2830: =D2829+IF(B2830<>B2829,E2829,0) -> 2779 | E2830: =COUNTIF(B:B,B2830) -> 57 | F2830: =MATCH(A2830,RLC!A:A,0) -> 1925 | G2830: {=INDEX(RLC!C:C,CorST!F2830)} -> 61.118685
A2831: широкого | B2831: 44 | C2831: 14.124239 | D2831: =D2830+IF(B2831<>B2830,E2830,0) -> 2779 | E2831: =COUNTIF(B:B,B2831) -> 57 | F2831: =MATCH(A2831,RLC!A:A,0) -> 5302 | G2831: {=INDEX(RLC!C:C,CorST!F2831)} -> 21.258673 | H2831: =C2831>F2831 -> FALSE
A2832: широкой | B2832: 44 | C2832: 14.124239 | D2832: =D2831+IF(B2832<>B2831,E2831,0) -> 2779 | E2832: =COUNTIF(B:B,B2832) -> 57 | F2832: =MATCH(A2832,RLC!A:A,0) -> 1998 | G2832: {=INDEX(RLC!C:C,CorST!F2832)} -> 58.46135 | H2832: =C2832>F2832 -> FALSE
A2833: экономиста | B2833: 44 | C2833: 14.124239 | D2833: =D2832+IF(B2833<>B2832,E2832,0) -> 2779 | E2833: =COUNTIF(B:B,B2833) -> 57 | F2833: =MATCH(A2833,RLC!A:A,0) -> #N/A | G2833: {=INDEX(RLC!C:C,CorST!F2833)} -> #N/A
A2834: экономического | B2834: 44 | C2834: 14.124239 | D2834: =D2833+IF(B2834<>B2833,E2833,0) -> 2779 | E2834: =COUNTIF(B:B,B2834) -> 57 | F2834: =MATCH(A2834,RLC!A:A,0) -> 917 | G2834: {=INDEX(RLC!C:C,CorST!F2834)} -> 120.9087
A2835: эксперта | B2835: 44 | C2835: 14.124239 | D2835: =D2834+IF(B2835<>B2834,E2834,0) -> 2779 | E2835: =COUNTIF(B:B,B2835) -> 57 | F2835: =MATCH(A2835,RLC!A:A,0) -> #N/A | G2835: {=INDEX(RLC!C:C,CorST!F2835)} -> #N/A
A2836: января | B2836: 44 | C2836: 14.124239 | D2836: =D2835+IF(B2836<>B2835,E2835,0) -> 2779 | E2836: =COUNTIF(B:B,B2836) -> 57 | F2836: =MATCH(A2836,RLC!A:A,0) -> 1413 | G2836: {=INDEX(RLC!C:C,CorST!F2836)} -> 81.04869
A2837: абстрактное | B2837: 43 | C2837: 13.803234 | D2837: =D2836+IF(B2837<>B2836,E2836,0) -> 2836 | E2837: =COUNTIF(B:B,B2837) -> 70 | F2837: =MATCH(A2837,RLC!A:A,0) -> #N/A | G2837: {=INDEX(RLC!C:C,CorST!F2837)} -> #N/A
A2838: автору | B2838: 43 | C2838: 13.803234 | D2838: =D2837+IF(B2838<>B2837,E2837,0) -> 2836 | E2838: =COUNTIF(B:B,B2838) -> 70 | F2838: =MATCH(A2838,RLC!A:A,0) -> 6004 | G2838: {=INDEX(RLC!C:C,CorST!F2838)} -> 17.272672
A2839: включая | B2839: 43 | C2839: 13.803234 | D2839: =D2838+IF(B2839<>B2838,E2838,0) -> 2836 | E2839: =COUNTIF(B:B,B2839) -> 70 | F2839: =MATCH(A2839,RLC!A:A,0) -> 1415 | G2839: {=INDEX(RLC!C:C,CorST!F2839)} -> 79.720023
A2840: встретить | B2840: 43 | C2840: 13.803234 | D2840: =D2839+IF(B2840<>B2839,E2839,0) -> 2836 | E2840: =COUNTIF(B:B,B2840) -> 70 | F2840: =MATCH(A2840,RLC!A:A,0) -> 4555 | G2840: {=INDEX(RLC!C:C,CorST!F2840)} -> 23.916007
A2841: выяснилось | B2841: 43 | C2841: 13.803234 | D2841: =D2840+IF(B2841<>B2840,E2840,0) -> 2836 | E2841: =COUNTIF(B:B,B2841) -> 70 | F2841: =MATCH(A2841,RLC!A:A,0) -> 6485 | G2841: {=INDEX(RLC!C:C,CorST!F2841)} -> 15.944005
A2842: грамматика | B2842: 43 | C2842: 13.803234 | D2842: =D2841+IF(B2842<>B2841,E2841,0) -> 2836 | E2842: =COUNTIF(B:B,B2842) -> 70 | F2842: =MATCH(A2842,RLC!A:A,0) -> 6065 | G2842: {=INDEX(RLC!C:C,CorST!F2842)} -> 17.272672
A2843: движений | B2843: 43 | C2843: 13.803234 | D2843: =D2842+IF(B2843<>B2842,E2842,0) -> 2836 | E2843: =COUNTIF(B:B,B2843) -> 70 | F2843: =MATCH(A2843,RLC!A:A,0) -> 4347 | G2843: {=INDEX(RLC!C:C,CorST!F2843)} -> 25.244674
A2844: доказывает | B2844: 43 | C2844: 13.803234 | D2844: =D2843+IF(B2844<>B2843,E2843,0) -> 2836 | E2844: =COUNTIF(B:B,B2844) -> 70 | F2844: =MATCH(A2844,RLC!A:A,0) -> 2364 | G2844: {=INDEX(RLC!C:C,CorST!F2844)} -> 47.832014
...

Sheet корст с рлс
A1: Word | B1: Частота-CorST | C1: IPM-CorST | D1: Ранг-CorST | E1: сколько раз встречается в столбце | F1: номер строки в rlc | G1: IPM_rlc
A2: в | B2: 35889 | C2: 11520.564 | D2: 1 | E2: =COUNTIF(B:B,B2) -> 1 | F2: =MATCH(A2,RLC!A:A,0) -> 3 | G2: {=INDEX(RLC!C:C,CorST!F2)} -> 37993.234
A3: и | B3: 31435 | C3: 10090.806 | D3: =D2+IF(B3<>B2,E2,0) -> 2 | E3: =COUNTIF(B:B,B3) -> 1 | F3: =MATCH(A3,RLC!A:A,0) -> 2 | G3: {=INDEX(RLC!C:C,CorST!F3)} -> 38334.702
A4: на | B4: 13212 | C4: 4241.1239 | D4: =D3+IF(B4<>B3,E3,0) -> 3 | E4: =COUNTIF(B:B,B4) -> 1 | F4: =MATCH(A4,RLC!A:A,0) -> 5 | G4: {=INDEX(RLC!C:C,CorST!F4)} -> 13265.412
A5: не | B5: 11811 | C5: 3791.3953 | D5: =D4+IF(B5<>B4,E4,0) -> 4 | E5: =COUNTIF(B:B,B5) -> 1 | F5: =MATCH(A5,RLC!A:A,0) -> 6 | G5: {=INDEX(RLC!C:C,CorST!F5)} -> 12860.168
A6: с | B6: 11363 | C6: 3647.5848 | D6: =D5+IF(B6<>B5,E5,0) -> 5 | E6: =COUNTIF(B:B,B6) -> 1 | F6: =MATCH(A6,RLC!A:A,0) -> 8 | G6: {=INDEX(RLC!C:C,CorST!F6)} -> 9178.432
A7: что | B7: 10265 | C7: 3295.1208 | D7: =D6+IF(B7<>B6,E6,0) -> 6 | E7: =COUNTIF(B:B,B7) -> 1 | F7: =MATCH(A7,RLC!A:A,0) -> 4 | G7: {=INDEX(RLC!C:C,CorST!F7)} -> 16305.402
A8: как | B8: 7396 | C8: 2374.1562 | D8: =D7+IF(B8<>B7,E7,0) -> 7 | E8: =COUNTIF(B:B,B8) -> 1 | F8: =MATCH(A8,RLC!A:A,0) -> 9 | G8: {=INDEX(RLC!C:C,CorST!F8)} -> 8273.6097
A9: к | B9: 6790 | C9: 2179.6269 | D9: =D8+IF(B9<>B8,E8,0) -> 8 | E9: =COUNTIF(B:B,B9) -> 1 | F9: =MATCH(A9,RLC!A:A,0) -> 15 | G9: {=INDEX(RLC!C:C,CorST!F9)} -> 4742.0127
A10: а | B10: 5924 | C10: 1901.6362 | D10: =D9+IF(B10<>B9,E9,0) -> 9 | E10: =COUNTIF(B:B,B10) -> 1 | F10: =MATCH(A10,RLC!A:A,0) -> 20 | G10: {=INDEX(RLC!C:C,CorST!F10)} -> 3449.2197
A11: для | B11: 5652 | C11: 1814.3227 | D11: =D10+IF(B11<>B10,E10,0) -> 10 | E11: =COUNTIF(B:B,B11) -> 1 | F11: =MATCH(A11,RLC!A:A,0) -> 14 | G11: {=INDEX(RLC!C:C,CorST!F11)} -> 5009.0748
A12: по | B12: 5634 | C12: 1808.5447 | D12: =D11+IF(B12<>B11,E11,0) -> 11 | E12: =COUNTIF(B:B,B12) -> 1 | F12: =MATCH(A12,RLC!A:A,0) -> 16 | G12: {=INDEX(RLC!C:C,CorST!F12)} -> 4641.034
A13: о | B13: 4912 | C13: 1576.7787 | D13: =D12+IF(B13<>B12,E12,0) -> 12 | E13: =COUNTIF(B:B,B13) -> 1 | F13: =MATCH(A13,RLC!A:A,0) -> 13 | G13: {=INDEX(RLC!C:C,CorST!F13)} -> 5022.3615
A14: из | B14: 4365 | C14: 1401.1887 | D14: =D13+IF(B14<>B13,E13,0) -> 13 | E14: =COUNTIF(B:B,B14) -> 1 | F14: =MATCH(A14,RLC!A:A,0) -> 17 | G14: {=INDEX(RLC!C:C,CorST!F14)} -> 4432.4333
... A1349: форм | B1349: 92 | C1349: 29.532501 | D1349: =D1348+IF(B1349<>B1348,E1348,0) -> 1326 | E1349: =COUNTIF(B:B,B1349) -> 26 | F1349: =MATCH(A1349,RLC!A:A,0) -> 5289 | G1349: {=INDEX(RLC!C:C,CorST!F1349)} -> 21.258673
A1350: школе | B1350: 92 | C1350: 29.532501 | D1350: =D1349+IF(B1350<>B1349,E1349,0) -> 1326 | E1350: =COUNTIF(B:B,B1350) -> 26 | F1350: =MATCH(A1350,RLC!A:A,0) -> 404 | G1350: {=INDEX(RLC!C:C,CorST!F1350)} -> 259.09008 | H1350: =C1350>F1350 -> FALSE
A1351: элементов | B1351: 92 | C1351: 29.532501 | D1351: =D1350+IF(B1351<>B1350,E1350,0) -> 1326 | E1351: =COUNTIF(B:B,B1351) -> 26 | F1351: =MATCH(A1351,RLC!A:A,0) -> 4112 | G1351: {=INDEX(RLC!C:C,CorST!F1351)} -> 27.902008
A1352: этими | B1352: 92 | C1352: 29.532501 | D1352: =D1351+IF(B1352<>B1351,E1351,0) -> 1326 | E1352: =COUNTIF(B:B,B1352) -> 26 | F1352: =MATCH(A1352,RLC!A:A,0) -> 1492 | G1352: {=INDEX(RLC!C:C,CorST!F1352)} -> 77.062689
A1353: артикля | B1353: 91 | C1353: 29.211495 | D1353: =D1352+IF(B1353<>B1352,E1352,0) -> 1352 | E1353: =COUNTIF(B:B,B1353) -> 12 | F1353: =MATCH(A1353,RLC!A:A,0) -> #N/A | G1353: {=INDEX(RLC!C:C,CorST!F1353)} -> #N/A
A1354: всему | B1354: 91 | C1354: 29.211495 | D1354: =D1353+IF(B1354<>B1353,E1353,0) -> 1352 | E1354: =COUNTIF(B:B,B1354) -> 12 | F1354: =MATCH(A1354,RLC!A:A,0) -> 741 | G1354: {=INDEX(RLC!C:C,CorST!F1354)} -> 144.82471
A1355: выполнения | B1355: 91 | C1355: 29.211495 | D1355: =D1354+IF(B1355<>B1354,E1354,0) -> 1352 | E1355: =COUNTIF(B:B,B1355) -> 12 | F1355: =MATCH(A1355,RLC!A:A,0) -> #N/A | G1355: {=INDEX(RLC!C:C,CorST!F1355)} -> #N/A
A1356: достоевский | B1356: 91 | C1356: 29.211495 | D1356: =D1355+IF(B1356<>B1355,E1355,0) -> 1352 | E1356: =COUNTIF(B:B,B1356) -> 12 | F1356: =MATCH(A1356,RLC!A:A,0) -> #N/A | G1356: {=INDEX(RLC!C:C,CorST!F1356)} -> #N/A
A1357: менеджмента | B1357: 91 | C1357: 29.211495 | D1357: =D1356+IF(B1357<>B1356,E1356,0) -> 1352 | E1357: =COUNTIF(B:B,B1357) -> 12 | F1357: =MATCH(A1357,RLC!A:A,0) -> 2858 | G1357: {=INDEX(RLC!C:C,CorST!F1357)} -> 39.860012
A1358: наша | B1358: 91 | C1358: 29.211495 | D1358: =D1357+IF(B1358<>B1357,E1357,0) -> 1352 | E1358: =COUNTIF(B:B,B1358) -> 12 | F1358: =MATCH(A1358,RLC!A:A,0) -> 551 | G1358: {=INDEX(RLC!C:C,CorST!F1358)} -> 193.98539
A1359: поднятая | B1359: 91 | C1359: 29.211495 | D1359: =D1358+IF(B1359<>B1358,E1358,0) -> 1352 | E1359: =COUNTIF(B:B,B1359) -> 12 | F1359: =MATCH(A1359,RLC!A:A,0) -> #N/A | G1359: {=INDEX(RLC!C:C,CorST!F1359)} -> #N/A
A1360: постепенно | B1360: 91 | C1360: 29.211495 | D1360: =D1359+IF(B1360<>B1359,E1359,0) -> 1352 | E1360: =COUNTIF(B:B,B1360) -> 12 | F1360: =MATCH(A1360,RLC!A:A,0) -> 2469 | G1360: {=INDEX(RLC!C:C,CorST!F1360)} -> 46.503347
A1361: рублей | B1361: 91 | C1361: 29.211495 | D1361: =D1360+IF(B1361<>B1360,E1360,0) -> 1352 | E1361: =COUNTIF(B:B,B1361) -> 12 | F1361: =MATCH(A1361,RLC!A:A,0) -> 1697 | G1361: {=INDEX(RLC!C:C,CorST!F1361)} -> 67.76202
A1362: сегодняшний | B1362: 91 | C1362: 29.211495 | D1362: =D1361+IF(B1362<>B1361,E1361,0) -> 1352 | E1362: =COUNTIF(B:B,B1362) -> 12 | F1362: =MATCH(A1362,RLC!A:A,0) -> 1873 | G1362: {=INDEX(RLC!C:C,CorST!F1362)} -> 62.447352
... A1716: чехов | B1716: 73 | C1716: 23.433397 | D1716: =D1715+IF(B1716<>B1715,E1715,0) -> 1684 | E1716: =COUNTIF(B:B,B1716) -> 35 | F1716: =MATCH(A1716,RLC!A:A,0) -> #N/A | G1716: {=INDEX(RLC!C:C,CorST!F1716)} -> #N/A
A1717: шапочка | B1717: 73 | C1717: 23.433397 | D1717: =D1716+IF(B1717<>B1716,E1716,0) -> 1684 | E1717: =COUNTIF(B:B,B1717) -> 35 | F1717: =MATCH(A1717,RLC!A:A,0) -> 3340 | G1717: {=INDEX(RLC!C:C,CorST!F1717)} -> 34.545343 | H1717: =C1717>F1717 -> FALSE
A1718: широко | B1718: 73 | C1718: 23.433397 | D1718: =D1717+IF(B1718<>B1717,E1717,0) -> 1684 | E1718: =COUNTIF(B:B,B1718) -> 35 | F1718: =MATCH(A1718,RLC!A:A,0) -> 1585 | G1718: {=INDEX(RLC!C:C,CorST!F1718)} -> 73.076688 | H1718: =C1718>F1718 -> FALSE
A1719: эмоций | B1719: 73 | C1719: 23.433397 | D1719: =D1718+IF(B1719<>B1718,E1718,0) -> 1684 | E1719: =COUNTIF(B:B,B1719) -> 35 | F1719: =MATCH(A1719,RLC!A:A,0) -> 6913 | G1719: {=INDEX(RLC!C:C,CorST!F1719)} -> 15.944005
A1720: большие | B1720: 72 | C1720: 23.112392 | D1720: =D1719+IF(B1720<>B1719,E1719,0) -> 1719 | E1720: =COUNTIF(B:B,B1720) -> 42 | F1720: =MATCH(A1720,RLC!A:A,0) -> 837 | G1720: {=INDEX(RLC!C:C,CorST!F1720)} -> 128.8807
A1721: большого | B1721: 72 | C1721: 23.112392 | D1721: =D1720+IF(B1721<>B1720,E1720,0) -> 1719 | E1721: =COUNTIF(B:B,B1721) -> 42 | F1721: =MATCH(A1721,RLC!A:A,0) -> 2651 | G1721: {=INDEX(RLC!C:C,CorST!F1721)} -> 42.517346
A1722: ведет | B1722: 72 | C1722: 23.112392 | D1722: =D1721+IF(B1722<>B1721,E1721,0) -> 1719 | E1722: =COUNTIF(B:B,B1722) -> 42 | F1722: =MATCH(A1722,RLC!A:A,0) -> 3483 | G1722: {=INDEX(RLC!C:C,CorST!F1722)} -> 31.888009
A1723: вниз | B1723: 72 | C1723: 23.112392 | D1723: =D1722+IF(B1723<>B1722,E1722,0) -> 1719 | E1723: =COUNTIF(B:B,B1723) -> 42 | F1723: =MATCH(A1723,RLC!A:A,0) -> 2832 | G1723: {=INDEX(RLC!C:C,CorST!F1723)} -> 39.860012
A1724: вузов | B1724: 72 | C1724: 23.112392 | D1724: =D1723+IF(B1724<>B1723,E1723,0) -> 1719 | E1724: =COUNTIF(B:B,B1724) -> 42 | F1724: =MATCH(A1724,RLC!A:A,0) -> 6052 | G1724: {=INDEX(RLC!C:C,CorST!F1724)} -> 17.272672
A1725: выражений | B1725: 72 | C1725: 23.112392 | D1725: =D1724+IF(B1725<>B1724,E1724,0) -> 1719 | E1725: =COUNTIF(B:B,B1725) -> 42 | F1725: =MATCH(A1725,RLC!A:A,0) -> 3786 | G1725: {=INDEX(RLC!C:C,CorST!F1725)} -> 29.230675
A1726: гражданским | B1726: 72 | C1726: 23.112392 | D1726: =D1725+IF(B1726<>B1725,E1725,0) -> 1719 | E1726: =COUNTIF(B:B,B1726) -> 42 | F1726: =MATCH(A1726,RLC!A:A,0) -> #N/A | G1726: {=INDEX(RLC!C:C,CorST!F1726)} -> #N/A
A1727: изучить | B1727: 72 | C1727: 23.112392 | D1727: =D1726+IF(B1727<>B1726,E1726,0) -> 1719 | E1727: =COUNTIF(B:B,B1727) -> 42 | F1727: =MATCH(A1727,RLC!A:A,0) -> 4372 | G1727: {=INDEX(RLC!C:C,CorST!F1727)} -> 25.244674
A1728: ин | B1728: 72 | C1728: 23.112392 | D1728: =D1727+IF(B1728<>B1727,E1727,0) -> 1719 | E1728: =COUNTIF(B:B,B1728) -> 42 | F1728: =MATCH(A1728,RLC!A:A,0) -> #N/A | G1728: {=INDEX(RLC!C:C,CorST!F1728)} -> #N/A
A1729: интернета | B1729: 72 | C1729: 23.112392 | D1729: =D1728+IF(B1729<>B1728,E1728,0) -> 1719 | E1729: =COUNTIF(B:B,B1729) -> 42 | F1729: =MATCH(A1729,RLC!A:A,0) -> 2960 | G1729: {=INDEX(RLC!C:C,CorST!F1729)} -> 38.531345
A1730: когнитивных | B1730: 72 | C1730: 23.112392 | D1730: =D1729+IF(B1730<>B1729,E1729,0) -> 1719 | E1730: =COUNTIF(B:B,B1730) -> 42 | F1730: =MATCH(A1730,RLC!A:A,0) -> #N/A | G1730: {=INDEX(RLC!C:C,CorST!F1730)} -> #N/A
... A2090: чтение | B2090: 61 | C2090: 19.581332 | D2090: =D2089+IF(B2090<>B2089,E2089,0) -> 2063 | E2090: =COUNTIF(B:B,B2090) -> 28 | F2090: =MATCH(A2090,RLC!A:A,0) -> 2647 | G2090: {=INDEX(RLC!C:C,CorST!F2090)} -> 43.846013
A2091: школы | B2091: 61 | C2091: 19.581332 | D2091: =D2090+IF(B2091<>B2090,E2090,0) -> 2063 | E2091: =COUNTIF(B:B,B2091) -> 28 | F2091: =MATCH(A2091,RLC!A:A,0) -> 542 | G2091: {=INDEX(RLC!C:C,CorST!F2091)} -> 197.97139 | H2091: =C2091>F2091 -> FALSE
A2092: больших | B2092: 60 | C2092: 19.260326 | D2092: =D2091+IF(B2092<>B2091,E2091,0) -> 2091 | E2092: =COUNTIF(B:B,B2092) -> 37 | F2092: =MATCH(A2092,RLC!A:A,0) -> 1082 | G2092: {=INDEX(RLC!C:C,CorST!F2092)} -> 102.30736
A2093: будем | B2093: 60 | C2093: 19.260326 | D2093: =D2092+IF(B2093<>B2092,E2092,0) -> 2091 | E2093: =COUNTIF(B:B,B2093) -> 37 | F2093: =MATCH(A2093,RLC!A:A,0) -> 1097 | G2093: {=INDEX(RLC!C:C,CorST!F2093)} -> 100.9787
A2094: вариативность | B2094: 60 | C2094: 19.260326 | D2094: =D2093+IF(B2094<>B2093,E2093,0) -> 2091 | E2094: =COUNTIF(B:B,B2094) -> 37 | F2094: =MATCH(A2094,RLC!A:A,0) -> #N/A | G2094: {=INDEX(RLC!C:C,CorST!F2094)} -> #N/A
A2095: возмещения | B2095: 60 | C2095: 19.260326 | D2095: =D2094+IF(B2095<>B2094,E2094,0) -> 2091 | E2095: =COUNTIF(B:B,B2095) -> 37 | F2095: =MATCH(A2095,RLC!A:A,0) -> #N/A | G2095: {=INDEX(RLC!C:C,CorST!F2095)} -> #N/A
A2096: возможностей | B2096: 60 | C2096: 19.260326 | D2096: =D2095+IF(B2096<>B2095,E2095,0) -> 2091 | E2096: =COUNTIF(B:B,B2096) -> 37 | F2096: =MATCH(A2096,RLC!A:A,0) -> 2835 | G2096: {=INDEX(RLC!C:C,CorST!F2096)} -> 39.860012
A2097: выяснить | B2097: 60 | C2097: 19.260326 | D2097: =D2096+IF(B2097<>B2096,E2096,0) -> 2091 | E2097: =COUNTIF(B:B,B2097) -> 37 | F2097: =MATCH(A2097,RLC!A:A,0) -> 7547 | G2097: {=INDEX(RLC!C:C,CorST!F2097)} -> 13.286671
A2098: гипотез | B2098: 60 | C2098: 19.260326 | D2098: =D2097+IF(B2098<>B2097,E2097,0) -> 2091 | E2098: =COUNTIF(B:B,B2098) -> 37 | F2098: =MATCH(A2098,RLC!A:A,0) -> #N/A | G2098: {=INDEX(RLC!C:C,CorST!F2098)} -> #N/A
A2099: голове | B2099: 60 | C2099: 19.260326 | D2099: =D2098+IF(B2099<>B2098,E2098,0) -> 2091 | E2099: =COUNTIF(B:B,B2099) -> 37 | F2099: =MATCH(A2099,RLC!A:A,0) -> 2131 | G2099: {=INDEX(RLC!C:C,CorST!F2099)} -> 53.146682
A2100: гражданском | B2100: 60 | C2100: 19.260326 | D2100: =D2099+IF(B2100<>B2099,E2099,0) -> 2091 | E2100: =COUNTIF(B:B,B2100) -> 37 | F2100: =MATCH(A2100,RLC!A:A,0) -> #N/A | G2100: {=INDEX(RLC!C:C,CorST!F2100)} -> #N/A
A2101: дается | B2101: 60 | C2101: 19.260326 | D2101: =D2100+IF(B2101<>B2100,E2100,0) -> 2091 | E2101: =COUNTIF(B:B,B2101) -> 37 | F2101: =MATCH(A2101,RLC!A:A,0) -> 4145 | G2101: {=INDEX(RLC!C:C,CorST!F2101)} -> 26.573341
A2102: дальнейшего | B2102: 60 | C2102: 19.260326 | D2102: =D2101+IF(B2102<>B2101,E2101,0) -> 2091 | E2102: =COUNTIF(B:B,B2102) -> 37 | F2102: =MATCH(A2102,RLC!A:A,0) -> #N/A | G2102: {=INDEX(RLC!C:C,CorST!F2102)} -> #N/A
A2103: другая | B2103: 60 | C2103: 19.260326 | D2103: =D2102+IF(B2103<>B2102,E2102,0) -> 2091 | E2103: =COUNTIF(B:B,B2103) -> 37 | F2103: =MATCH(A2103,RLC!A:A,0) -> 1157 | G2103: {=INDEX(RLC!C:C,CorST!F2103)} -> 96.992695
... A2510: фоне | B2510: 50 | C2510: 16.050272 | D2510: =D2509+IF(B2510<>B2509,E2509,0) -> 2456 | E2510: =COUNTIF(B:B,B2510) -> 55 | F2510: =MATCH(A2510,RLC!A:A,0) -> #N/A | G2510: {=INDEX(RLC!C:C,CorST!F2510)} -> #N/A
A2511: широкий | B2511: 50 | C2511: 16.050272 | D2511: =D2510+IF(B2511<>B2510,E2510,0) -> 2456 | E2511: =COUNTIF(B:B,B2511) -> 55 | F2511: =MATCH(A2511,RLC!A:A,0) -> 6907 | G2511: {=INDEX(RLC!C:C,CorST!F2511)} -> 15.944005 | H2511: =C2511>F2511 -> FALSE
A2512: адресован | B2512: 49 | C2512: 15.729267 | D2512: =D2511+IF(B2512<>B2511,E2511,0) -> 2511 | E2512: =COUNTIF(B:B,B2512) -> 45 | F2512: =MATCH(A2512,RLC!A:A,0) -> #N/A | G2512: {=INDEX(RLC!C:C,CorST!F2512)} -> #N/A
A2513: база | B2513: 49 | C2513: 15.729267 | D2513: =D2512+IF(B2513<>B2512,E2512,0) -> 2511 | E2513: =COUNTIF(B:B,B2513) -> 45 | F2513: =MATCH(A2513,RLC!A:A,0) -> #N/A | G2513: {=INDEX(RLC!C:C,CorST!F2513)} -> #N/A
A2514: вариативности | B2514: 49 | C2514: 15.729267 | D2514: =D2513+IF(B2514<>B2513,E2513,0) -> 2511 | E2514: =COUNTIF(B:B,B2514) -> 45 | F2514: =MATCH(A2514,RLC!A:A,0) -> #N/A | G2514: {=INDEX(RLC!C:C,CorST!F2514)} -> #N/A
A2515: введения | B2515: 49 | C2515: 15.729267 | D2515: =D2514+IF(B2515<>B2514,E2514,0) -> 2511 | E2515: =COUNTIF(B:B,B2515) -> 45 | F2515: =MATCH(A2515,RLC!A:A,0) -> 7509 | G2515: {=INDEX(RLC!C:C,CorST!F2515)} -> 13.286671
A2516: видел | B2516: 49 | C2516: 15.729267 | D2516: =D2515+IF(B2516<>B2515,E2515,0) -> 2511 | E2516: =COUNTIF(B:B,B2516) -> 45 | F2516: =MATCH(A2516,RLC!A:A,0) -> 1926 | G2516: {=INDEX(RLC!C:C,CorST!F2516)} -> 59.790017
A2517: высокий | B2517: 49 | C2517: 15.729267 | D2517: =D2516+IF(B2517<>B2516,E2516,0) -> 2511 | E2517: =COUNTIF(B:B,B2517) -> 45 | F2517: =MATCH(A2517,RLC!A:A,0) -> 2129 | G2517: {=INDEX(RLC!C:C,CorST!F2517)} -> 53.146682
A2518: выходит | B2518: 49 | C2518: 15.729267 | D2518: =D2517+IF(B2518<>B2517,E2517,0) -> 2511 | E2518: =COUNTIF(B:B,B2518) -> 45 | F2518: =MATCH(A2518,RLC!A:A,0) -> 3637 | G2518: {=INDEX(RLC!C:C,CorST!F2518)} -> 30.559342
A2519: герои | B2519: 49 | C2519: 15.729267 | D2519: =D2518+IF(B2519<>B2518,E2518,0) -> 2511 | E2519: =COUNTIF(B:B,B2519) -> 45 | F2519: =MATCH(A2519,RLC!A:A,0) -> 2502 | G2519: {=INDEX(RLC!C:C,CorST!F2519)} -> 45.17468
A2520: глагольных | B2520: 49 | C2520: 15.729267 | D2520: =D2519+IF(B2520<>B2519,E2519,0) -> 2511 | E2520: =COUNTIF(B:B,B2520) -> 45 | F2520: =MATCH(A2520,RLC!A:A,0) -> #N/A | G2520: {=INDEX(RLC!C:C,CorST!F2520)} -> #N/A
A2521: гпк | B2521: 49 | C2521: 15.729267 | D2521: =D2520+IF(B2521<>B2520,E2520,0) -> 2511 | E2521: =COUNTIF(B:B,B2521) -> 45 | F2521: =MATCH(A2521,RLC!A:A,0) -> #N/A | G2521: {=INDEX(RLC!C:C,CorST!F2521)} -> #N/A
A2522: егэ | B2522: 49 | C2522: 15.729267 | D2522: =D2521+IF(B2522<>B2521,E2521,0) -> 2511 | E2522: =COUNTIF(B:B,B2522) -> 45 | F2522: =MATCH(A2522,RLC!A:A,0) -> 3049 | G2522: {=INDEX(RLC!C:C,CorST!F2522)} -> 37.202678
A2523: единственный | B2523: 49 | C2523: 15.729267 | D2523: =D2522+IF(B2523<>B2522,E2522,0) -> 2511 | E2523: =COUNTIF(B:B,B2523) -> 45 | F2523: =MATCH(A2523,RLC!A:A,0) -> 1892 | G2523: {=INDEX(RLC!C:C,CorST!F2523)} -> 61.118685
... A2664: человеке | B2664: 47 | C2664: 15.087256 | D2664: =D2663+IF(B2664<>B2663,E2663,0) -> 2608 | E2664: =COUNTIF(B:B,B2664) -> 57 | F2664: =MATCH(A2664,RLC!A:A,0) -> 2556 | G2664: {=INDEX(RLC!C:C,CorST!F2664)} -> 45.17468
A2665: шаг | B2665: 47 | C2665: 15.087256 | D2665: =D2664+IF(B2665<>B2664,E2664,0) -> 2608 | E2665: =COUNTIF(B:B,B2665) -> 57 | F2665: =MATCH(A2665,RLC!A:A,0) -> 2738 | G2665: {=INDEX(RLC!C:C,CorST!F2665)} -> 42.517346 | H2665: =C2665>F2665 -> FALSE
A2666: авторских | B2666: 46 | C2666: 14.76625 | D2666: =D2665+IF(B2666<>B2665,E2665,0) -> 2665 | E2666: =COUNTIF(B:B,B2666) -> 72 | F2666: =MATCH(A2666,RLC!A:A,0) -> #N/A | G2666: {=INDEX(RLC!C:C,CorST!F2666)} -> #N/A
A2667: будь | B2667: 46 | C2667: 14.76625 | D2667: =D2666+IF(B2667<>B2666,E2666,0) -> 2665 | E2667: =COUNTIF(B:B,B2667) -> 72 | F2667: =MATCH(A2667,RLC!A:A,0) -> 3245 | G2667: {=INDEX(RLC!C:C,CorST!F2667)} -> 34.545343
A2668: бытия | B2668: 46 | C2668: 14.76625 | D2668: =D2667+IF(B2668<>B2667,E2667,0) -> 2665 | E2668: =COUNTIF(B:B,B2668) -> 72 | F2668: =MATCH(A2668,RLC!A:A,0) -> #N/A | G2668: {=INDEX(RLC!C:C,CorST!F2668)} -> #N/A
A2669: вводит | B2669: 46 | C2669: 14.76625 | D2669: =D2668+IF(B2669<>B2668,E2668,0) -> 2665 | E2669: =COUNTIF(B:B,B2669) -> 72 | F2669: =MATCH(A2669,RLC!A:A,0) -> #N/A | G2669: {=INDEX(RLC!C:C,CorST!F2669)} -> #N/A
A2670: вещь | B2670: 46 | C2670: 14.76625 | D2670: =D2669+IF(B2670<>B2669,E2669,0) -> 2665 | E2670: =COUNTIF(B:B,B2670) -> 72 | F2670: =MATCH(A2670,RLC!A:A,0) -> 2655 | G2670: {=INDEX(RLC!C:C,CorST!F2670)} -> 42.517346
A2671: взаимодействии | B2671: 46 | C2671: 14.76625 | D2671: =D2670+IF(B2671<>B2670,E2670,0) -> 2665 | E2671: =COUNTIF(B:B,B2671) -> 72 | F2671: =MATCH(A2671,RLC!A:A,0) -> #N/A | G2671: {=INDEX(RLC!C:C,CorST!F2671)} -> #N/A
A2672: выборки | B2672: 46 | C2672: 14.76625 | D2672: =D2671+IF(B2672<>B2671,E2671,0) -> 2665 | E2672: =COUNTIF(B:B,B2672) -> 72 | F2672: =MATCH(A2672,RLC!A:A,0) -> #N/A | G2672: {=INDEX(RLC!C:C,CorST!F2672)} -> #N/A
A2673: выделены | B2673: 46 | C2673: 14.76625 | D2673: =D2672+IF(B2673<>B2672,E2672,0) -> 2665 | E2673: =COUNTIF(B:B,B2673) -> 72 | F2673: =MATCH(A2673,RLC!A:A,0) -> #N/A | G2673: {=INDEX(RLC!C:C,CorST!F2673)} -> #N/A
A2674: гипотезу | B2674: 46 | C2674: 14.76625 | D2674: =D2673+IF(B2674<>B2673,E2673,0) -> 2665 | E2674: =COUNTIF(B:B,B2674) -> 72 | F2674: =MATCH(A2674,RLC!A:A,0) -> #N/A | G2674: {=INDEX(RLC!C:C,CorST!F2674)} -> #N/A
A2675: государств | B2675: 46 | C2675: 14.76625 | D2675: =D2674+IF(B2675<>B2674,E2674,0) -> 2665 | E2675: =COUNTIF(B:B,B2675) -> 72 | F2675: =MATCH(A2675,RLC!A:A,0) -> 991 | G2675: {=INDEX(RLC!C:C,CorST!F2675)} -> 111.60803
A2676: доме | B2676: 46 | C2676: 14.76625 | D2676: =D2675+IF(B2676<>B2675,E2675,0) -> 2665 | E2676: =COUNTIF(B:B,B2676) -> 72 | F2676: =MATCH(A2676,RLC!A:A,0) -> 907 | G2676: {=INDEX(RLC!C:C,CorST!F2676)} -> 120.9087
A2677: думать | B2677: 46 | C2677: 14.76625 | D2677: =D2676+IF(B2677<>B2676,E2676,0) -> 2665 | E2677: =COUNTIF(B:B,B2677) -> 72 | F2677: =MATCH(A2677,RLC!A:A,0) -> 720 | G2677: {=INDEX(RLC!C:C,CorST!F2677)} -> 147.48204
... A2830: ценностей | B2830: 44 | C2830: 14.124239 | D2830: =D2829+IF(B2830<>B2829,E2829,0) -> 2779 | E2830: =COUNTIF(B:B,B2830) -> 57 | F2830: =MATCH(A2830,RLC!A:A,0) -> 1925 | G2830: {=INDEX(RLC!C:C,CorST!F2830)} -> 61.118685
A2831: широкого | B2831: 44 | C2831: 14.124239 | D2831: =D2830+IF(B2831<>B2830,E2830,0) -> 2779 | E2831: =COUNTIF(B:B,B2831) -> 57 | F2831: =MATCH(A2831,RLC!A:A,0) -> 5302 | G2831: {=INDEX(RLC!C:C,CorST!F2831)} -> 21.258673 | H2831: =C2831>F2831 -> FALSE
A2832: широкой | B2832: 44 | C2832: 14.124239 | D2832: =D2831+IF(B2832<>B2831,E2831,0) -> 2779 | E2832: =COUNTIF(B:B,B2832) -> 57 | F2832: =MATCH(A2832,RLC!A:A,0) -> 1998 | G2832: {=INDEX(RLC!C:C,CorST!F2832)} -> 58.46135 | H2832: =C2832>F2832 -> FALSE
A2833: экономиста | B2833: 44 | C2833: 14.124239 | D2833: =D2832+IF(B2833<>B2832,E2832,0) -> 2779 | E2833: =COUNTIF(B:B,B2833) -> 57 | F2833: =MATCH(A2833,RLC!A:A,0) -> #N/A | G2833: {=INDEX(RLC!C:C,CorST!F2833)} -> #N/A
A2834: экономического | B2834: 44 | C2834: 14.124239 | D2834: =D2833+IF(B2834<>B2833,E2833,0) -> 2779 | E2834: =COUNTIF(B:B,B2834) -> 57 | F2834: =MATCH(A2834,RLC!A:A,0) -> 917 | G2834: {=INDEX(RLC!C:C,CorST!F2834)} -> 120.9087
A2835: эксперта | B2835: 44 | C2835: 14.124239 | D2835: =D2834+IF(B2835<>B2834,E2834,0) -> 2779 | E2835: =COUNTIF(B:B,B2835) -> 57 | F2835: =MATCH(A2835,RLC!A:A,0) -> #N/A | G2835: {=INDEX(RLC!C:C,CorST!F2835)} -> #N/A
A2836: января | B2836: 44 | C2836: 14.124239 | D2836: =D2835+IF(B2836<>B2835,E2835,0) -> 2779 | E2836: =COUNTIF(B:B,B2836) -> 57 | F2836: =MATCH(A2836,RLC!A:A,0) -> 1413 | G2836: {=INDEX(RLC!C:C,CorST!F2836)} -> 81.04869
A2837: абстрактное | B2837: 43 | C2837: 13.803234 | D2837: =D2836+IF(B2837<>B2836,E2836,0) -> 2836 | E2837: =COUNTIF(B:B,B2837) -> 70 | F2837: =MATCH(A2837,RLC!A:A,0) -> #N/A | G2837: {=INDEX(RLC!C:C,CorST!F2837)} -> #N/A
A2838: автору | B2838: 43 | C2838: 13.803234 | D2838: =D2837+IF(B2838<>B2837,E2837,0) -> 2836 | E2838: =COUNTIF(B:B,B2838) -> 70 | F2838: =MATCH(A2838,RLC!A:A,0) -> 6004 | G2838: {=INDEX(RLC!C:C,CorST!F2838)} -> 17.272672
A2839: включая | B2839: 43 | C2839: 13.803234 | D2839: =D2838+IF(B2839<>B2838,E2838,0) -> 2836 | E2839: =COUNTIF(B:B,B2839) -> 70 | F2839: =MATCH(A2839,RLC!A:A,0) -> 1415 | G2839: {=INDEX(RLC!C:C,CorST!F2839)} -> 79.720023
A2840: встретить | B2840: 43 | C2840: 13.803234 | D2840: =D2839+IF(B2840<>B2839,E2839,0) -> 2836 | E2840: =COUNTIF(B:B,B2840) -> 70 | F2840: =MATCH(A2840,RLC!A:A,0) -> 4555 | G2840: {=INDEX(RLC!C:C,CorST!F2840)} -> 23.916007
A2841: выяснилось | B2841: 43 | C2841: 13.803234 | D2841: =D2840+IF(B2841<>B2840,E2840,0) -> 2836 | E2841: =COUNTIF(B:B,B2841) -> 70 | F2841: =MATCH(A2841,RLC!A:A,0) -> 6485 | G2841: {=INDEX(RLC!C:C,CorST!F2841)} -> 15.944005
A2842: грамматика | B2842: 43 | C2842: 13.803234 | D2842: =D2841+IF(B2842<>B2841,E2841,0) -> 2836 | E2842: =COUNTIF(B:B,B2842) -> 70 | F2842: =MATCH(A2842,RLC!A:A,0) -> 6065 | G2842: {=INDEX(RLC!C:C,CorST!F2842)} -> 17.272672
A2843: движений | B2843: 43 | C2843: 13.803234 | D2843: =D2842+IF(B2843<>B2842,E2842,0) -> 2836 | E2843: =COUNTIF(B:B,B2843) -> 70 | F2843: =MATCH(A2843,RLC!A:A,0) -> 4347 | G2843: {=INDEX(RLC!C:C,CorST!F2843)} -> 25.244674
A2844: доказывает | B2844: 43 | C2844: 13.803234 | D2844: =D2843+IF(B2844<>B2843,E2843,0) -> 2836 | E2844: =COUNTIF(B:B,B2844) -> 70 | F2844: =MATCH(A2844,RLC!A:A,0) -> 2364 | G2844: {=INDEX(RLC!C:C,CorST!F2844)} -> 47.832014
...

Sheet merge
A1: Word | B1: IPM-CorST | C1: IPM_rlc
A2: а | B2: 1901.6362 | C2: 3449.2197
A3: аббревиатуры | B3: 4.4940762
A4: абзац | B4: 86.029458 | C4: 75.734022
A5: абзаца | B5: 51.039865
A6: абзаце | B6: 43.014729 | C6: 23.916007
A7: абзацев | B7: 12.198207
A8: абзацу | B8: 3.5310598
A9: абзацы | B9: 43.65674
A10: абитуриентов | B10: 3.2100544 | C10: 27.902008
A11: абитуриенты | C11: 15.944005
A12: абрамова | B12: 3.2100544
A13: абсолютно | B13: 35.631604 | C13: 81.04869
A14: абсолютной | B14: 4.1730707
A15: абстрагироваться | B15: 5.4570925
A16: абстрактного | B16: 6.7411142
A17: абстрактное | B17: 13.803234
A18: абстрактном | B18: 3.5310598
A19: абстрактные | B19: 8.6671469 | C19: 14.615338
A20: абстрактный | B20: 4.1730707
A21: абстрактным | B21: 6.0991034
A22: абстрактными | B22: 3.2100544
A23: абстрактных | B23: 5.4570925
A24: абсурд | B24: 3.2100544
A25: абсурда | B25: 9.3091578 | C25: 13.286671
A26: авангард | C26: 14.615338
A27: авангарда | C27: 43.846013
A28: авангардистов | C28: 15.944005
A29: авангардные | C29: 15.944005
A30: аварии | C30: 38.531345
A31: авария | C31: 14.615338
A32: август | B32: 18.29731
A33: августа | B33: 25.680435 | C33: 57.132683
A34: августе | C34: 13.286671
A35: австрийский | B35: 6.4201088
A36: австрийского | B36: 5.4570925
A37: автобиографическое | B37: 4.8150816
A38: автобиография | B38: 3.2100544
A39: автобус | B39: 3.8520653 | C39: 14.615338
A40: автобусе | C40: 17.272672
A41: автолюбителей | B41: 5.4570925
A42: автоматизмов | B42: 3.8520653
A43: автоматизмы | B43: 5.136087
A44: автоматически | B44: 6.0991034
A45: автомобилей | B45: 8.3461415
A46: автомобилистов | B46: 4.8150816
A47: автомобиль | B47: 17.976305
A48: автомобильная | B48: 15.408261
A49: автомобильной | B49: 7.7041306
A50: автомобильных | B50: 3.8520653
A51: автомобиля | B51: 4.1730707
A52: автоперевозки | B52: 3.2100544
A53: автор | B53: 503.65754 | C53: 964.61228
A54: автора | B54: 112.99392 | C54: 223.21607
A55: авторам | B55: 5.4570925
A56: авторами | B56: 14.445245
A57: авторитет | B57: 17.334294 | C57: 23.916007
A58: авторитетом | B58: 5.136087
A59: авторов | B59: 35.952609 | C59: 37.202678
A60: автором | B60: 94.375599 | C60: 46.503347
A61: авторская | B61: 7.0621197
A62: авторские | B62: 3.2100544
A63: авторских | B63: 14.76625
A64: авторского | B64: 14.124239
A65: авторское | B65: 7.3831251
A66: авторской | B66: 16.692283
A67: авторском | B67: 3.5310598
A68: авторства | B68: 3.2100544
A69: авторство | B69: 3.8520653
A70: автору | B70: 13.803234 | C70: 17.272672
A71: авторы | B71: 77.683317 | C71: 111.60803
A72: автошколах | B72: 3.5310598
A73: агенство | C73: 15.944005
A74: агентства | B74: 3.8520653
A75: агентство | B75: 3.5310598
A76: ад | B76: 4.8150816
A77: ада | B77: 4.8150816
A78: адаптации | B78: 16.371277 | C78: 26.573341
A79: адаптацию | B79: 3.5310598
A80: адаптация | B80: 6.4201088 | C80: 14.615338
A81: адаптироваться | C81: 37.202678
A82: адвербиальный | B82: 4.4940762
A83: адвокат | B83: 7.7041306
A84: адвоката | B84: 5.7780979
A85: адвокатов | B85: 3.5310598
A86: адвокаты | B86: 4.1730707
A87: адекватно | B87: 5.136087
A88: адекватного | B88: 4.8150816
A89: административная | B89: 3.2100544
A90: административно-правовые | B90: 6.4201088
A91: административно-правовых | B91: 12.519212
A92: административного | B92: 12.519212
A93: административное | B93: 6.0991034
... A96: административных | B96: 9.9511687
A97: администрации | B97: 4.8150816 | C97: 13.286671
A98: адрес | B98: 8.9881523
A99: адресантом | B99: 3.2100544
A100: адресат | B100: 10.272174
A101: адресата | B101: 9.9511687
A102: адресатом | B102: 9.6301632
...

Sheet RLC
A1: Word | B1: Частота-RLC | C1: IPM-RLC | D1: Ранг-RLC | E1: сколько раз встречается число в столбце | F1: номер строки в CorST
A2: и | B2: 28852 | C2: 38334.702 | D2: 1 | E2: =COUNTIF(B:B,B2) -> 1 | F2: =MATCH(A2,CorST!A:A,0) -> 3
A3: в | B3: 28595 | C3: 37993.234 | D3: =D2+IF(B3<>B2,E2,0) -> 2 | E3: =COUNTIF(B:B,B3) -> 1 | F3: =MATCH(A3,CorST!A:A,0) -> 2
A4: что | B4: 12272 | C4: 16305.402 | D4: =D3+IF(B4<>B3,E3,0) -> 3 | E4: =COUNTIF(B:B,B4) -> 1 | F4: =MATCH(A4,CorST!A:A,0) -> 7
A5: на | B5: 9984 | C5: 13265.412 | D5: =D4+IF(B5<>B4,E4,0) -> 4 | E5: =COUNTIF(B:B,B5) -> 1 | F5: =MATCH(A5,CorST!A:A,0) -> 4
A6: не | B6: 9679 | C6: 12860.168 | D6: =D5+IF(B6<>B5,E5,0) -> 5 | E6: =COUNTIF(B:B,B6) -> 1 | F6: =MATCH(A6,CorST!A:A,0) -> 5
A7: я | B7: 8489 | C7: 11279.055 | D7: =D6+IF(B7<>B6,E6,0) -> 6 | E7: =COUNTIF(B:B,B7) -> 1 | F7: =MATCH(A7,CorST!A:A,0) -> 24
A8: с | B8: 6908 | C8: 9178.432 | D8: =D7+IF(B8<>B7,E7,0) -> 7 | E8: =COUNTIF(B:B,B8) -> 1 | F8: =MATCH(A8,CorST!A:A,0) -> 6
A9: как | B9: 6227 | C9: 8273.6097 | D9: =D8+IF(B9<>B8,E8,0) -> 8 | E9: =COUNTIF(B:B,B9) -> 1 | F9: =MATCH(A9,CorST!A:A,0) -> 8
A10: это | B10: 5389 | C10: 7160.1868 | D10: =D9+IF(B10<>B9,E9,0) -> 9 | E10: =COUNTIF(B:B,B10) -> 1 | F10: =MATCH(A10,CorST!A:A,0) -> 15
A11: но | B11: 4307 | C11: 5722.569 | D11: =D10+IF(B11<>B10,E10,0) -> 10 | E11: =COUNTIF(B:B,B11) -> 1 | F11: =MATCH(A11,CorST!A:A,0) -> 19
A12: он | B12: 4050 | C12: 5381.1016 | D12: =D11+IF(B12<>B11,E11,0) -> 11 | E12: =COUNTIF(B:B,B12) -> 1 | F12: =MATCH(A12,CorST!A:A,0) -> 21
A13: о | B13: 3780 | C13: 5022.3615 | D13: =D12+IF(B13<>B12,E12,0) -> 12 | E13: =COUNTIF(B:B,B13) -> 1 | F13: =MATCH(A13,CorST!A:A,0) -> 13
A14: для | B14: 3770 | C14: 5009.0748 | D14: =D13+IF(B14<>B13,E13,0) -> 13 | E14: =COUNTIF(B:B,B14) -> 1 | F14: =MATCH(A14,CorST!A:A,0) -> 11
... A8127: японский | B8127: 10 | C8127: 13.286671 | D8127: =D8126+IF(B8127<>B8126,E8126,0) -> 7471 | E8127: =COUNTIF(B:B,B8127) -> 656 | F8127: =MATCH(A8127,CorST!A:A,0) -> #N/A
